HP23005UNO/__init__.py
HP23005UNO/equation_solver/__init__.py
HP23005UNO/equation_solver/linear.py
HP23005UNO/equation_solver/nonlinear.py
hp23005uno-0.1.6.dist-info/METADATA
hp23005uno-0.1.6.dist-info/WHEEL
hp23005uno-0.1.6.dist-info/top_level.txt
hp23005uno-0.1.6.dist-info/RECORD
